{
  "action": {
    "description": "(S) 11:05 A.M. 7/20/26 Transmitted to Governor",
    "occurred_at": "2026-07-20",
    "jurisdiction_id": "~{\"classification\": \"upper\"}",
    "session_id": "34",
    "entity_type": "bill",
    "classifications": [
      "executive-receipt"
    ],
    "related_entities": [],
    "sources": [
      {
        "url": "https://www.akleg.gov/basis/Bill/Detail/34?Root=SB143",
        "note": ""
      },
      {
        "url": "https://www.akleg.gov/basis/Bill/Detail/34?Root=SB143#tab5_4",
        "note": ""
      }
    ]
  },
  "bill_id": "SB143"
}