{
  "legislative_session": "34",
  "identifier": "HB187",
  "title": "An Act relating to the membership of the legislative council; and relating to the membership of the Legislative Budget and Audit Committee.",
  "from_organization": "~{\"classification\": \"lower\"}",
  "classification": [
    "bill"
  ],
  "subject": [
    "LEGISLATIVE COMMITTEES",
    "LEGISLATURE",
    "POLITICAL PARTIES"
  ],
  "abstracts": [],
  "other_titles": [],
  "other_identifiers": [
    {
      "identifier": "ocd-bill-ak-34-hb187"
    }
  ],
  "actions": [
    {
      "description": "(H) READ THE FIRST TIME - REFERRALS",
      "date": "2025-04-11",
      "organization_id": "~{\"classification\": \"lower\"}",
      "classification": [
        "reading-1"
      ],
      "related_entities": [],
      "_processing": {
        "log_file_created": "2026-07-13T06:02:00Z"
      }
    },
    {
      "description": "(H) STA",
      "date": "2025-04-11",
      "organization_id": "~{\"classification\": \"lower\"}",
      "classification": [],
      "related_entities": [],
      "_processing": {
        "log_file_created": "2026-07-13T06:02:00Z"
      }
    },
    {
      "description": "(H) STATE AFFAIRS at 03:15 PM GRUENBERG 120",
      "date": "2026-04-30",
      "organization_id": "~{\"classification\": \"lower\"}",
      "classification": [],
      "related_entities": [],
      "_processing": {
        "log_file_created": "2026-07-14T13:55:27Z"
      }
    },
    {
      "description": "(H) Heard & Held",
      "date": "2026-04-30",
      "organization_id": "~{\"classification\": \"lower\"}",
      "classification": [],
      "related_entities": [],
      "_processing": {
        "log_file_created": "2026-07-14T13:55:27Z"
      }
    },
    {
      "description": "(H) STATE AFFAIRS at 03:15 PM GRUENBERG 120",
      "date": "2026-05-05",
      "organization_id": "~{\"classification\": \"lower\"}",
      "classification": [],
      "related_entities": [],
      "_processing": {
        "log_file_created": "2026-07-14T13:55:27Z"
      }
    },
    {
      "description": "(H) Moved HB 187 Out of Committee",
      "date": "2026-05-05",
      "organization_id": "~{\"classification\": \"lower\"}",
      "classification": [],
      "related_entities": [],
      "_processing": {
        "log_file_created": "2026-07-14T13:55:27Z"
      }
    },
    {
      "description": "(H) STA RPT 7DP",
      "date": "2026-05-06",
      "organization_id": "~{\"classification\": \"lower\"}",
      "classification": [],
      "related_entities": [],
      "_processing": {
        "log_file_created": "2026-07-14T13:55:27Z"
      }
    },
    {
      "description": "(H) DP: VANCE, MCCABE, ST. CLAIR, HOLLAND, HIMSCHOOT, STORY, CARRICK",
      "date": "2026-05-06",
      "organization_id": "~{\"classification\": \"lower\"}",
      "classification": [],
      "related_entities": [],
      "_processing": {
        "log_file_created": "2026-07-14T13:55:27Z"
      }
    },
    {
      "description": "(H) FN1: ZERO(LEG)",
      "date": "2026-05-06",
      "organization_id": "~{\"classification\": \"lower\"}",
      "classification": [],
      "related_entities": [],
      "_processing": {
        "log_file_created": "2026-07-14T13:55:27Z"
      }
    },
    {
      "description": "(H) REFERRED TO RULES",
      "date": "2026-05-06",
      "organization_id": "~{\"classification\": \"lower\"}",
      "classification": [
        "referral-committee"
      ],
      "related_entities": [],
      "_processing": {
        "log_file_created": "2026-07-14T13:55:27Z"
      }
    },
    {
      "description": "(H) COSPONSOR(S): MCCABE",
      "date": "2026-05-07",
      "organization_id": "~{\"classification\": \"lower\"}",
      "classification": [],
      "related_entities": [],
      "_processing": {
        "log_file_created": "2026-07-14T13:55:27Z"
      }
    }
  ],
  "sponsorships": [
    {
      "name": "Costello",
      "classification": "primary",
      "entity_type": "person",
      "primary": true,
      "person_id": "~{\"chamber\": \"lower\", \"name\": \"Costello\"}",
      "organization_id": null
    },
    {
      "name": "Mccabe",
      "classification": "cosponsor",
      "entity_type": "person",
      "primary": false,
      "person_id": "~{\"chamber\": \"lower\", \"name\": \"Mccabe\"}",
      "organization_id": null
    }
  ],
  "related_bills": [],
  "versions": [
    {
      "note": "HB 187",
      "links": [
        {
          "url": "https://www.akleg.gov/basis/Bill/Text/34?Hsid=HB0187A",
          "media_type": "text/html"
        },
        {
          "url": "https://www.akleg.gov/PDF/34/Bills/HB0187A.PDF",
          "media_type": "application/pdf"
        }
      ],
      "date": "",
      "classification": ""
    }
  ],
  "documents": [
    {
      "note": "Sponsor Statement",
      "links": [
        {
          "url": "http://www.akleg.gov/basis/get_documents.asp?session=34&docid=15014",
          "media_type": "pdf"
        }
      ],
      "date": "",
      "classification": ""
    },
    {
      "note": "HB 187 Backup Legislative Research",
      "links": [
        {
          "url": "https://www.akleg.gov/basis/get_documents.asp?session=34&docid=15426",
          "media_type": "pdf"
        }
      ],
      "date": "",
      "classification": ""
    },
    {
      "note": "HB187 FIscal Note LEG-COUN-04-29-26",
      "links": [
        {
          "url": "https://www.akleg.gov/basis/get_documents.asp?session=34&docid=15088",
          "media_type": "pdf"
        }
      ],
      "date": "",
      "classification": ""
    },
    {
      "note": "HB 187 Sectional Analysis Version A",
      "links": [
        {
          "url": "https://www.akleg.gov/basis/get_documents.asp?session=34&docid=15015",
          "media_type": "pdf"
        }
      ],
      "date": "",
      "classification": ""
    },
    {
      "note": "HB 187 Sponsor Statement Version A",
      "links": [
        {
          "url": "https://www.akleg.gov/basis/get_documents.asp?session=34&docid=15014",
          "media_type": "pdf"
        }
      ],
      "date": "",
      "classification": ""
    },
    {
      "note": "HB 187 Version A",
      "links": [
        {
          "url": "https://www.akleg.gov/basis/get_documents.asp?session=34&docid=15013",
          "media_type": "pdf"
        }
      ],
      "date": "",
      "classification": ""
    }
  ],
  "citations": [],
  "sources": [
    {
      "url": "https://www.akleg.gov/basis/Bill/Detail/34?Root=HB187",
      "note": ""
    },
    {
      "url": "https://www.akleg.gov/basis/Bill/Detail/34?Root=HB187#tab5_4",
      "note": ""
    }
  ],
  "extras": {},
  "jurisdiction": {
    "id": "ocd-jurisdiction/country:us/state:ak/government",
    "name": "Alaska",
    "classification": "state",
    "division_id": "ocd-division/country:us/state:ak"
  },
  "_processing": {
    "logs_latest_update": "2026-07-14T13:55:27Z",
    "text_extraction_latest_update": "2026-07-13T06:27:02.934532Z"
  }
}