{
  "identifier": "",
  "motion_text": "(S) PASSED Y16 N4 #2890",
  "motion_classification": [
    "passage"
  ],
  "start_date": "2026-05-20",
  "result": "pass",
  "organization": "~{\"classification\": \"upper\"}",
  "legislative_session": "34",
  "bill": "19ec6758-7f59-11f1-8cb7-3258ed82ccdb",
  "bill_action": null,
  "bill_identifier": "SCR28",
  "votes": [],
  "counts": [
    {
      "option": "yes",
      "value": 16
    },
    {
      "option": "no",
      "value": 4
    },
    {
      "option": "other",
      "value": 0
    }
  ],
  "sources": [
    {
      "url": "https://www.akleg.gov/basis/Journal/Pages/34?Chamber=S&Bill=SCR28&Page=02890#2890",
      "note": ""
    }
  ],
  "extras": {}
}