{
  "legislative_session": "34",
  "identifier": "HCR22",
  "title": "Suspending Rules 24(c), 35, 41(b), and 42(e), Uniform Rules of the Alaska State Legislature, concerning Senate Bill No. 170, relating to gaming; relating to gaming activities on Alaska marine highway system vessels; relating to bingo; relating to pull-tabs and electronic pull-tab systems; relating to the powers of the Department of Transportation and Public Facilities; and relating to the Alaska marine highway system fund.",
  "from_organization": "~{\"classification\": \"lower\"}",
  "classification": [
    "concurrent resolution"
  ],
  "subject": [
    "BUSINESS",
    "CONTRACTS",
    "GAMBLING",
    "LICENSING",
    "PERMITS",
    "REVENUE",
    "SALES",
    "TAXATION",
    "UNIFORM RULES"
  ],
  "abstracts": [],
  "other_titles": [],
  "other_identifiers": [
    {
      "identifier": "ocd-bill-ak-34-hcr22"
    }
  ],
  "actions": [
    {
      "description": "(H) READ THE FIRST TIME",
      "date": "2026-05-15",
      "organization_id": "~{\"classification\": \"lower\"}",
      "classification": [
        "reading-1"
      ],
      "related_entities": [],
      "_processing": {
        "log_file_created": "2026-07-14T13:55:25Z"
      }
    }
  ],
  "sponsorships": [
    {
      "name": "House Labor & Commerce",
      "classification": "primary",
      "entity_type": "organization",
      "primary": true,
      "person_id": null,
      "organization_id": "~{\"chamber\": \"lower\", \"name\": \"House Labor & Commerce\"}"
    }
  ],
  "related_bills": [],
  "versions": [
    {
      "note": "HCR 22",
      "links": [
        {
          "url": "https://www.akleg.gov/basis/Bill/Text/34?Hsid=HCR022A",
          "media_type": "text/html"
        },
        {
          "url": "https://www.akleg.gov/PDF/34/Bills/HCR022A.PDF",
          "media_type": "application/pdf"
        }
      ],
      "date": "",
      "classification": ""
    }
  ],
  "documents": [],
  "citations": [],
  "sources": [
    {
      "url": "https://www.akleg.gov/basis/Bill/Detail/34?Root=HCR22",
      "note": ""
    },
    {
      "url": "https://www.akleg.gov/basis/Bill/Detail/34?Root=HCR22#tab5_4",
      "note": ""
    }
  ],
  "extras": {},
  "jurisdiction": {
    "id": "ocd-jurisdiction/country:us/state:ak/government",
    "name": "Alaska",
    "classification": "state",
    "division_id": "ocd-division/country:us/state:ak"
  },
  "_processing": {
    "logs_latest_update": "2026-07-14T13:55:25Z",
    "text_extraction_latest_update": "2026-07-14T20:28:51.704544Z"
  }
}