{
  "identifier": "",
  "motion_text": "(H) RETURN TO SECOND FOR AMS FAILED Y19 N21 #2140",
  "motion_classification": [
    "passage"
  ],
  "start_date": "2026-04-13",
  "result": "fail",
  "organization": "~{\"classification\": \"lower\"}",
  "legislative_session": "34",
  "bill": "2cb40130-7f58-11f1-8cb7-3258ed82ccdb",
  "bill_action": null,
  "bill_identifier": "HB263",
  "votes": [],
  "counts": [
    {
      "option": "yes",
      "value": 19
    },
    {
      "option": "no",
      "value": 21
    },
    {
      "option": "other",
      "value": 0
    }
  ],
  "sources": [
    {
      "url": "https://www.akleg.gov/basis/Journal/Pages/34?Chamber=H&Bill=HB263&Page=02140#2140",
      "note": ""
    }
  ],
  "extras": {}
}