{
  "action": {
    "description": "(H) JUDICIARY at 01:00 PM GRUENBERG 120",
    "occurred_at": "2025-05-12",
    "jurisdiction_id": "~{\"classification\": \"lower\"}",
    "session_id": "34",
    "entity_type": "bill",
    "classifications": [],
    "related_entities": [],
    "sources": [
      {
        "url": "https://www.akleg.gov/basis/Bill/Detail/34?Root=HB209",
        "note": ""
      },
      {
        "url": "https://www.akleg.gov/basis/Bill/Detail/34?Root=HB209#tab5_4",
        "note": ""
      }
    ]
  },
  "bill_id": "HB209"
}