{
  "action": {
    "description": "(S) PRIME SPONSOR CHANGED - SENATE HEALTH AND SOCIAL SERVICES COMMITTEE",
    "occurred_at": "2025-03-14",
    "jurisdiction_id": "~{\"classification\": \"upper\"}",
    "session_id": "34",
    "entity_type": "bill",
    "classifications": [],
    "related_entities": [],
    "sources": [
      {
        "url": "https://www.akleg.gov/basis/Bill/Detail/34?Root=SB95",
        "note": ""
      },
      {
        "url": "https://www.akleg.gov/basis/Bill/Detail/34?Root=SB95#tab5_4",
        "note": ""
      }
    ]
  },
  "bill_id": "SB95"
}