{
  "legislative_session": "34",
  "identifier": "HB284",
  "title": "An Act relating to the Multistate Tax Compact; relating to apportionment of income to the state; establishing a state sales and use tax; relating to taxes levied by cities and boroughs; relating to the corporate income tax; authorizing the Department of Revenue to enter into the Streamlined Sales and Use Tax Agreement or substantially similar agreement; relating to the oil and gas production tax; establishing an infrastructure maintenance surcharge on oil; establishing a pipeline corridor maintenance fund; and providing for an effective date.",
  "from_organization": "~{\"classification\": \"lower\"}",
  "classification": [
    "bill"
  ],
  "subject": [
    "ALCOHOL",
    "AUDITS",
    "BOARDS & COMMISSIONS",
    "BUSINESS",
    "COMPACTS",
    "CONSUMER AFFAIRS",
    "CONTRACTS",
    "CORPORATIONS",
    "COURTS",
    "CREDIT",
    "FINANCE",
    "FISH & GAME (FISH)",
    "FUNDS",
    "INTERGOVERNMENTAL RELATIONS",
    "LEASES",
    "LIABILITY",
    "LICENSING",
    "MARIJUANA",
    "MOTOR VEHICLES",
    "MUNICIPALITIES",
    "OIL & GAS",
    "PERMITS",
    "PIPELINES",
    "PROPERTY",
    "PUBLIC FINANCE",
    "REVENUE",
    "SALES",
    "TAXATION",
    "TOBACCO",
    "UNIFORM ACTS",
    "WAGES"
  ],
  "abstracts": [],
  "other_titles": [],
  "other_identifiers": [
    {
      "identifier": "ocd-bill-ak-34-hb284"
    }
  ],
  "actions": [
    {
      "description": "(H) READ THE FIRST TIME - REFERRALS",
      "date": "2026-01-28",
      "organization_id": "~{\"classification\": \"lower\"}",
      "classification": [
        "reading-1"
      ],
      "related_entities": [],
      "_processing": {
        "log_file_created": "2026-07-14T13:55:26Z"
      }
    },
    {
      "description": "(H) FIN",
      "date": "2026-01-28",
      "organization_id": "~{\"classification\": \"lower\"}",
      "classification": [],
      "related_entities": [],
      "_processing": {
        "log_file_created": "2026-07-14T13:55:26Z"
      }
    },
    {
      "description": "(H) FN1: (REV)",
      "date": "2026-01-28",
      "organization_id": "~{\"classification\": \"lower\"}",
      "classification": [],
      "related_entities": [],
      "_processing": {
        "log_file_created": "2026-07-14T13:55:26Z"
      }
    },
    {
      "description": "(H) GOVERNOR'S TRANSMITTAL LETTER",
      "date": "2026-01-28",
      "organization_id": "~{\"classification\": \"lower\"}",
      "classification": [],
      "related_entities": [],
      "_processing": {
        "log_file_created": "2026-07-14T13:55:26Z"
      }
    },
    {
      "description": "(H) REFERRED TO FINANCE",
      "date": "2026-01-28",
      "organization_id": "~{\"classification\": \"lower\"}",
      "classification": [
        "referral-committee"
      ],
      "related_entities": [],
      "_processing": {
        "log_file_created": "2026-07-14T13:55:26Z"
      }
    },
    {
      "description": "(H) FINANCE at 09:00 AM ADAMS 519",
      "date": "2026-02-05",
      "organization_id": "~{\"classification\": \"lower\"}",
      "classification": [],
      "related_entities": [],
      "_processing": {
        "log_file_created": "2026-07-14T13:55:26Z"
      }
    },
    {
      "description": "(H) Heard & Held -- Please Note Time Change --",
      "date": "2026-02-05",
      "organization_id": "~{\"classification\": \"lower\"}",
      "classification": [],
      "related_entities": [],
      "_processing": {
        "log_file_created": "2026-07-14T13:55:26Z"
      }
    },
    {
      "description": "(H) Minutes (HFIN)",
      "date": "2026-02-05",
      "organization_id": "~{\"classification\": \"lower\"}",
      "classification": [],
      "related_entities": [],
      "_processing": {
        "log_file_created": "2026-07-14T13:55:26Z"
      }
    },
    {
      "description": "(H) FINANCE at 01:30 PM ADAMS 519",
      "date": "2026-02-05",
      "organization_id": "~{\"classification\": \"lower\"}",
      "classification": [],
      "related_entities": [],
      "_processing": {
        "log_file_created": "2026-07-14T13:55:26Z"
      }
    },
    {
      "description": "(H) Heard & Held",
      "date": "2026-02-05",
      "organization_id": "~{\"classification\": \"lower\"}",
      "classification": [],
      "related_entities": [],
      "_processing": {
        "log_file_created": "2026-07-14T13:55:26Z"
      }
    },
    {
      "description": "(H) Minutes (HFIN)",
      "date": "2026-02-05",
      "organization_id": "~{\"classification\": \"lower\"}",
      "classification": [],
      "related_entities": [],
      "_processing": {
        "log_file_created": "2026-07-14T13:55:26Z"
      }
    },
    {
      "description": "(H) FINANCE at 05:30 PM ADAMS 519",
      "date": "2026-02-05",
      "organization_id": "~{\"classification\": \"lower\"}",
      "classification": [],
      "related_entities": [],
      "_processing": {
        "log_file_created": "2026-07-14T13:55:26Z"
      }
    },
    {
      "description": "(H) Heard & Held -- Please Note Time Change --",
      "date": "2026-02-05",
      "organization_id": "~{\"classification\": \"lower\"}",
      "classification": [],
      "related_entities": [],
      "_processing": {
        "log_file_created": "2026-07-14T13:55:26Z"
      }
    },
    {
      "description": "(H) Minutes (HFIN)",
      "date": "2026-02-05",
      "organization_id": "~{\"classification\": \"lower\"}",
      "classification": [],
      "related_entities": [],
      "_processing": {
        "log_file_created": "2026-07-14T13:55:26Z"
      }
    },
    {
      "description": "(H) FINANCE at 01:30 PM ADAMS 519",
      "date": "2026-02-12",
      "organization_id": "~{\"classification\": \"lower\"}",
      "classification": [],
      "related_entities": [],
      "_processing": {
        "log_file_created": "2026-07-14T13:55:26Z"
      }
    },
    {
      "description": "(H) Heard & Held",
      "date": "2026-02-12",
      "organization_id": "~{\"classification\": \"lower\"}",
      "classification": [],
      "related_entities": [],
      "_processing": {
        "log_file_created": "2026-07-14T13:55:26Z"
      }
    }
  ],
  "sponsorships": [
    {
      "name": "House Rules",
      "classification": "primary",
      "entity_type": "organization",
      "primary": true,
      "person_id": null,
      "organization_id": "~{\"chamber\": \"lower\", \"name\": \"House Rules\"}"
    }
  ],
  "related_bills": [],
  "versions": [
    {
      "note": "HB 284",
      "links": [
        {
          "url": "https://www.akleg.gov/basis/Bill/Text/34?Hsid=HB0284A",
          "media_type": "text/html"
        },
        {
          "url": "https://www.akleg.gov/PDF/34/Bills/HB0284A.PDF",
          "media_type": "application/pdf"
        }
      ],
      "date": "",
      "classification": ""
    }
  ],
  "documents": [
    {
      "note": "HB284 Intro Presentation to H.FIN Appendix 02.05.26 030626",
      "links": [
        {
          "url": "https://www.akleg.gov/basis/get_documents.asp?session=34&docid=11284",
          "media_type": "pdf"
        }
      ],
      "date": "",
      "classification": ""
    },
    {
      "note": "HB284 House Finance Economic Impacts Summary Report 030626",
      "links": [
        {
          "url": "https://www.akleg.gov/basis/get_documents.asp?session=34&docid=11283",
          "media_type": "pdf"
        }
      ],
      "date": "",
      "classification": ""
    },
    {
      "note": "HB 284 DOR Response to H.FIN  on 02.12.26 362026",
      "links": [
        {
          "url": "https://www.akleg.gov/basis/get_documents.asp?session=34&docid=11282",
          "media_type": "pdf"
        }
      ],
      "date": "",
      "classification": ""
    },
    {
      "note": "HB 284 Public Testimony Recd by 021126pm_R",
      "links": [
        {
          "url": "https://www.akleg.gov/basis/get_documents.asp?session=34&docid=9703",
          "media_type": "pdf"
        }
      ],
      "date": "",
      "classification": ""
    },
    {
      "note": "HB 284 DOR Response to H.FIN on 02.05.26 021126",
      "links": [
        {
          "url": "https://www.akleg.gov/basis/get_documents.asp?session=34&docid=9638",
          "media_type": "pdf"
        }
      ],
      "date": "",
      "classification": ""
    },
    {
      "note": "HB 284 Public Testimony Recd by 020626_R",
      "links": [
        {
          "url": "https://www.akleg.gov/basis/get_documents.asp?session=34&docid=9338",
          "media_type": "pdf"
        }
      ],
      "date": "",
      "classification": ""
    },
    {
      "note": "HB284 DOR Intro Presentation to H.FIN 02.05.26",
      "links": [
        {
          "url": "https://www.akleg.gov/basis/get_documents.asp?session=34&docid=9251",
          "media_type": "pdf"
        }
      ],
      "date": "",
      "classification": ""
    },
    {
      "note": "HB 284 AML Alaska Fiscal Policy - Sales Tax 020426",
      "links": [
        {
          "url": "https://www.akleg.gov/basis/get_documents.asp?session=34&docid=9218",
          "media_type": "pdf"
        }
      ],
      "date": "",
      "classification": ""
    },
    {
      "note": "HB284 Transmittal Letter 01.26.26",
      "links": [
        {
          "url": "https://www.akleg.gov/basis/get_documents.asp?session=34&docid=9065",
          "media_type": "pdf"
        }
      ],
      "date": "",
      "classification": ""
    },
    {
      "note": "HB284 Sectional Analysis version A 1.28.2026",
      "links": [
        {
          "url": "https://www.akleg.gov/basis/get_documents.asp?session=34&docid=9064",
          "media_type": "pdf"
        }
      ],
      "date": "",
      "classification": ""
    },
    {
      "note": "HB 284 Governor Dunleavy\u00e2\u20ac\u2122s Fiscal Plan - Comparative Modeling Scenarios - 01.26.2026",
      "links": [
        {
          "url": "https://www.akleg.gov/basis/get_documents.asp?session=34&docid=9063",
          "media_type": "pdf"
        }
      ],
      "date": "",
      "classification": ""
    }
  ],
  "citations": [],
  "sources": [
    {
      "url": "https://www.akleg.gov/basis/Bill/Detail/34?Root=HB284",
      "note": ""
    },
    {
      "url": "https://www.akleg.gov/basis/Bill/Detail/34?Root=HB284#tab5_4",
      "note": ""
    }
  ],
  "extras": {},
  "jurisdiction": {
    "id": "ocd-jurisdiction/country:us/state:ak/government",
    "name": "Alaska",
    "classification": "state",
    "division_id": "ocd-division/country:us/state:ak"
  },
  "_processing": {
    "logs_latest_update": "2026-07-14T13:55:26Z",
    "text_extraction_latest_update": "2026-07-14T20:41:44.051229Z"
  }
}